[{"id": "13225", "quote": "Information is not knowledge.", "author": "Albert Einstein", "category": "knowledge", "tags": ["information", "knowledge"], "popularity": 0.000308000308000308}, {"id": "33668", "quote": "Information is what you put in empty heads to keep them empty.", "author": "Marty Rubin", "category": "knowledge", "tags": ["ignorance", "information", "knowledge"], "popularity": 3.000003000003e-06}, {"id": "31257", "quote": "What information consumes is rather obvious: it consumes the attention of its recipients. Hence a wealth of information creates a poverty of attention, and a need to allocate that attention efficiently among the overabundance of information sources that might consume it.", "author": "Herbert Simon", "category": "philosophy", "tags": ["philosophy"], "popularity": 1.000001000001e-05}, {"id": "34168", "quote": "The purpose of collecting so much information can only be power.", "author": "Nick Drake,  Nefertiti: The Book of the Dead", "category": "knowledge", "tags": ["information", "knowledge", "power"], "popularity": 2.000002000002e-06}, {"id": "12912", "quote": "I do not know everything; still many things I understand.", "author": "Madeleine L'Engle,  A Wrinkle in Time", "category": "wisdom", "tags": ["wisdom"], "popularity": 0.000324000324000324}, {"id": "30322", "quote": "But this wealth of information produced little or no insight.", "author": "Stephen King,  The Gunslinger", "category": "philosophy", "tags": ["modernism", "philosophy"], "popularity": 1.4000014000014e-05}, {"id": "32246", "quote": "You don’t know anything, but I know even less.", "author": "Dejan Stojanovic,  The Sun Watches the Sun", "category": "knowledge", "tags": ["anything", "books", "dejan-stojanovic", "knowledge", "less", "literature", "literature-quotes", "philosophy", "poetry", "poetry-quotes", "poets", "quotes", "the-sun-watches-the-sun", "wisdom"], "popularity": 7.000007000007e-06}, {"id": "30864", "quote": "All we know is what we're told.", "author": "Ashly Lorenzana", "category": "knowledge", "tags": ["acceptance", "knowledge", "life", "perception", "reality", "subjectivity", "trust", "truth"], "popularity": 1.2000012000012e-05}, {"id": "8265", "quote": "The public have an insatiable curiosity to know everything, except what is worth knowing.", "author": "Oscar Wilde,  The Soul of Man Under Socialism, and Selected Critical Prose", "category": "wisdom", "tags": ["curiosity", "epigram", "tabloid-journalism", "wisdom"], "popularity": 0.001159001159001159}, {"id": "25123", "quote": "Stuff your brain with knowledge.", "author": "Karl Lagerfeld", "category": "quotes", "tags": ["brain", "chanel", "designer", "educational", "karl-lagerfeld", "knownledge", "life", "mind", "quotes", "stuff", "success", "wisdom"], "popularity": 4.7000047000047e-05}, {"id": "7276", "quote": "The more I read, the more I acquire, the more certain I am that I know nothing.", "author": "Voltaire", "category": "wisdom", "tags": ["learning", "self-knowledge", "wisdom"], "popularity": 0.001675001675001675}, {"id": "22077", "quote": "I only know that I know nothing", "author": "Socrates", "category": "philosophy", "tags": ["creative-thinking", "intellect", "knowledge", "philosophy", "wisdom"], "popularity": 7.8000078000078e-05}, {"id": "31651", "quote": "I only know everything if you ask the right questions.", "author": "Doc Coleman", "category": "knowledge", "tags": ["humor", "knowledge", "wisdom-quote"], "popularity": 9.000009000009e-06}, {"id": "35292", "quote": "Too Much Information You must empty your mind of garbage to let new garbage in.", "author": "Beryl Dov", "category": "philosophy", "tags": ["death", "faith", "god", "happiness", "hope", "humor", "inspirational-quotes", "knowing-oneself", "knowledge", "knowledge-education", "knowledge-of-self", "knowledge-teaching", "life", "love", "master", "master-key", "master-of-love", "masters", "mastery", "meaning", "meditation", "mind", "mind-body-spirit", "mind-power", "personal-development", "personal-growth", "philosophy", "poetry", "positive-attitude", "positive-mindset", "positive-motivation", "positive-outlook", "positive-quotes", "positive-thinking", "positive-thoughts", "power-of-love", "power-of-thoughts", "power-of-words", "powerful-story", "purpose", "quote", "relationships", "sacred", "sacred-teachings", "sacred-wisdom", "sage", "sage-advice", "self-esteem-self-help-book", "self-improvement", "self-improvement-book", "soul", "soul-searching", "spirit", "spiritual-development", "spiritual-growth", "spiritual-wisdom", "spiritualism", "suicidal-thoughts", "suicide", "teachings", "truth", "unconditional-acceptance", "unconditional-love", "wisdom"], "popularity": 0}, {"id": "36491", "quote": "Knowledgeable [10w] The knowledgeable man inventoried and catalogued everything he doesn't know.", "author": "Beryl Dov", "category": "mind", "tags": ["death", "faith", "god", "happiness", "hope", "humor", "inspirational-quotes", "knowing-oneself", "knowledge", "knowledge-education", "knowledge-of-self", "knowledge-teaching", "life", "love", "master", "master-key", "master-of-love", "masters", "mastery", "meaning", "meditation", "mind", "mind-body-spirit", "mind-power", "personal-development", "personal-growth", "philosophy", "poetry", "positive-attitude", "positive-mindset", "positive-motivation", "positive-outlook", "positive-quotes", "positive-thinking", "positive-thoughts", "power-of-love", "power-of-thoughts", "power-of-words", "powerful-story", "purpose", "quote", "relationships", "sacred", "sacred-teachings", "sacred-wisdom", "sage", "sage-advice", "self-esteem-self-help-book", "self-improvement", "self-improvement-book", "soul", "soul-searching", "spirit", "spiritual-development", "spiritual-growth", "spiritual-wisdom", "spiritualism", "suicidal-thoughts", "suicide", "teachings", "truth", "unconditional-acceptance", "unconditional-love", "wisdom"], "popularity": 0}, {"id": "36283", "quote": "Keenly seek knowledge.", "author": "Lailah Gifty Akita", "category": "education", "tags": ["education", "knowledge", "motivational", "self-improvement", "wisdom-of-lailah-gifty-akita"], "popularity": 0}, {"id": "23835", "quote": "We understand more than we know.", "author": "Margaret Atwood,  Oryx and Crake", "category": "knowledge", "tags": ["knowledge", "science", "understanding", "wisdom"], "popularity": 5.8000058000058e-05}, {"id": "16206", "quote": "Everything I know, I know because of love.", "author": "Leo Tolstoy,  War and Peace", "category": "love", "tags": ["fiction", "love"], "popularity": 0.000196000196000196}, {"id": "27714", "quote": "Since we cannot know all there is to be known about anything, we ought to know a little about everything.", "author": "Blaise Pascal", "category": "knowledge", "tags": ["knowledge"], "popularity": 2.8000028000028e-05}, {"id": "17321", "quote": "Write what you know.", "author": "Mark Twain,  The Adventures of Tom Sawyer & Adventures of Huckleberry Finn", "category": "writing", "tags": ["writing"], "popularity": 0.000167000167000167}, {"id": "15811", "quote": "Everybody gets so much information all day long that they lose their common sense.", "author": "Gertrude Stein", "category": "wisdom", "tags": ["knowledge", "wisdom"], "popularity": 0.000209000209000209}, {"id": "29744", "quote": "I don't write about what I know: I write in order to find out what I know.", "author": "Patricia Hampl", "category": "knowledge", "tags": ["imagination", "knowledge", "memory", "writing"], "popularity": 1.7000017000017e-05}, {"id": "15892", "quote": "Everything you need to know you have learned through your journey.", "author": "Paulo Coelho,  The Alchemist", "category": "inspiration", "tags": ["deep-thought", "inspiration", "soul-seeking"], "popularity": 0.000207000207000207}, {"id": "32255", "quote": "The knowledge that we consider knowledge proves itself in action. What we now mean by knowledge is information in action, information focused on results.", "author": "Peter F. Drucker", "category": "knowledge", "tags": ["action", "knowledge", "optimism"], "popularity": 7.000007000007e-06}, {"id": "24032", "quote": "Where is the wisdom we have lost in knowledge?Where is the knowledge we have lost in infomation?", "author": "T.S. Eliot", "category": "knowledge", "tags": ["information", "knowledge", "wisdom"], "popularity": 5.6000056000056e-05}, {"id": "29976", "quote": "Isn’t that wonderful? That feeling of not knowing too much about something… Incomplete information… Endless possibilities… When you don’t know much about something, it’s the most exciting sensation.-Kutsnetz in TALUS", "author": "Erol Ozan,  Talus", "category": "knowledge", "tags": ["endless-possibility", "incomplete-information", "information", "knowledge", "mystery", "sensation", "unknown"], "popularity": 1.6000016000016e-05}, {"id": "34151", "quote": "On Knowledge: You know that I know you know, but I want you to know that I know you know I know you know I know. It’s important for you to know that, you know?", "author": "Jarod Kintz,  This Book is Not FOR SALE", "category": "knowledge", "tags": ["humor", "knowledge"], "popularity": 2.000002000002e-06}, {"id": "4505", "quote": "I'm not young enough to know everything.", "author": "J.M. Barrie,  The Admirable Crichton", "category": "wisdom", "tags": ["wisdom"], "popularity": 0.003509003509003509}, {"id": "30424", "quote": "An educated man should know everything about something and something about everything", "author": "C.V. Wedgwood", "category": "knowledge", "tags": ["education", "knowledge"], "popularity": 1.4000014000014e-05}, {"id": "31382", "quote": "Curiosity is a call from knowledge.", "author": "Toba Beta,  My Ancestor Was an Ancient Astronaut", "category": "knowledge", "tags": ["call", "curiosity", "knowledge"], "popularity": 1.000001000001e-05}, {"id": "34208", "quote": "The higher knowledge, the higher responsibility", "author": "Muhammad Ahkam A", "category": "inspiration", "tags": ["inspiration"], "popularity": 2.000002000002e-06}, {"id": "24482", "quote": "Knowledge is of two kinds. We know a subject ourselves, or we know where we can find information on it.", "author": "Samuel Johnson", "category": "knowledge", "tags": ["information", "knowledge"], "popularity": 5.2000052000052e-05}, {"id": "10363", "quote": "People know what they do; frequently they know why they do what they do; but what they don't know is what what they do does.", "author": "Michel Foucault,  Madness and Civilization: A History of Insanity in the Age of Reason", "category": "philosophy", "tags": ["philosophy", "wisdom"], "popularity": 0.000581000581000581}, {"id": "17835", "quote": "When my information changes, I alter my conclusions. What do you do, sir?", "author": "John Maynard Keynes", "category": "science", "tags": ["open-mindedness", "science"], "popularity": 0.000154000154000154}, {"id": "36430", "quote": "Begin to acquire knowledge.", "author": "Lailah Gifty Akita", "category": "education", "tags": ["education", "knowledge", "self-discovery"], "popularity": 0}, {"id": "28556", "quote": "Facts? What are facts? I only know imagination!", "author": "C. JoyBell C.", "category": "inspiration", "tags": ["belief", "facts", "imagination", "inspirational", "inspirational-quotes", "inspire"], "popularity": 2.3000023000023e-05}, {"id": "18245", "quote": "Wikipedia is the first place I go when I'm looking for knowledge... or when I want to create some.", "author": "Stephen Colbert", "category": "humor", "tags": ["humor", "wikipedia"], "popularity": 0.000144000144000144}, {"id": "29882", "quote": "True knowledge exists in knowing that you know nothing.", "author": "Socrates", "category": "philosophy", "tags": ["philosophy"], "popularity": 1.6000016000016e-05}, {"id": "10122", "quote": "I go to school, but I never learn what I want to know.", "author": "Bill Watterson,  The Authoritative Calvin And Hobbes", "category": "education", "tags": ["education"], "popularity": 0.000625000625000625}, {"id": "22078", "quote": "To know that we know what we know, and to know that we do not know what we do not know, that is true knowledge.", "author": "Nicolaus Copernicus", "category": "wisdom", "tags": ["copernicus", "knowledge", "wisdom"], "popularity": 7.8000078000078e-05}, {"id": "33708", "quote": "It is important to know the stories and histories of things, even if all we know is that we don't know.", "author": "Ali Smith,  There But for The", "category": "knowledge", "tags": ["history", "ignorance", "knowledge", "stories"], "popularity": 3.000003000003e-06}, {"id": "36268", "quote": "I seek and search for the light of knowledge.", "author": "Lailah Gifty Akita", "category": "education", "tags": ["education", "knowledge", "seek"], "popularity": 0}, {"id": "32985", "quote": "You know you made it, when people you know, tell people they know, that you know them.", "author": "Mokokoma Mokhonoana", "category": "success", "tags": ["failure", "name-dropping", "show-off", "success"], "popularity": 5.000005000005e-06}, {"id": "8993", "quote": "People don't care how much you know until they know how much you care", "author": "Theodore Roosevelt", "category": "knowledge", "tags": ["customer-service", "knowledge"], "popularity": 0.00089000089000089}, {"id": "25752", "quote": "I can't protect you from knowledge.", "author": "Patricia Briggs,  Dragon Bones", "category": "knowledge", "tags": ["knowledge"], "popularity": 4.2000042000042e-05}, {"id": "2531", "quote": "I am not young enough to know everything.", "author": "Oscar Wilde", "category": "other", "tags": ["age"], "popularity": 0.007017007017007017}, {"id": "5890", "quote": "Don't waste your time with explanations: people only hear what they want to hear.", "author": "Paulo Coelho", "category": "life", "tags": ["attitude", "explain", "gossip", "life", "people", "public-opinion", "time", "wisdom"], "popularity": 0.002426002426002426}, {"id": "30413", "quote": "What can I say? I prefer to die well informed.", "author": "Nalini Singh,  Angels' Blood", "category": "knowledge", "tags": ["death", "elena", "guild-hunter", "humor", "knowledge", "life", "nalini-sighn", "vampires"], "popularity": 1.4000014000014e-05}, {"id": "16887", "quote": "All I know is just what I read in the papers, and that's an alibi for my ignorance.", "author": "Will Rogers", "category": "humor", "tags": ["funny", "humor", "media"], "popularity": 0.000179000179000179}, {"id": "19512", "quote": "The problems are solved, not by giving new information, but by arranging what we have known since long.", "author": "Ludwig Wittgenstein,  Philosophical Investigations", "category": "knowledge", "tags": ["information", "knowledge", "problems"], "popularity": 0.000118000118000118}]